IR/IRDipoleApprox.py
IR/__init__.py
IR_JaGeo-1.0.4.dist-info/LICENSE
IR_JaGeo-1.0.4.dist-info/METADATA
IR_JaGeo-1.0.4.dist-info/WHEEL
IR_JaGeo-1.0.4.dist-info/top_level.txt
IR_JaGeo-1.0.4.dist-info/RECORD
