Metadata-Version: 2.1
Name: IR-JaGeo
Version: 1.0.4
Summary: Package to calculate infrared ntensities with the dipole approximation
Home-page: https://github.com/JaGeo/IR
Author: Janine George
Author-email: janine.george@uclouvain.be
License: UNKNOWN
Platform: UNKNOWN
Classifier: Programming Language :: Python :: 3
Classifier: License :: OSI Approved :: BSD License
Classifier: Operating System :: OS Independent
Requires-Dist: phonopy (>=2.1.1)
